{
  "name": "ai-input-01",
  "type": "registry:component",
  "dependencies": [
    "lucide-react"
  ],
  "registryDependencies": [
    "textarea"
  ],
  "files": [
    {
      "type": "registry:component",
      "content": "'use client'\r\n\r\nimport { useState } from \"react\"\r\nimport { cn } from \"../../lib/utils\"\r\nimport { Input } from \"../../components/ui/input\"\r\nimport { Textarea } from \"../../components/ui/textarea\"\r\nimport { CornerRightUp, Mic } from \"lucide-react\"\r\nimport { useAutoResizeTextarea } from \"../../hooks/use-auto-resize-textarea\"\r\n\r\nexport default function AIInput_01() {\r\n    const { textareaRef, adjustHeight } = useAutoResizeTextarea({ minHeight: 50, maxHeight: 200 });\r\n    const [inputValue, setInputValue] = useState(\"\")\r\n    const handleReset = () => {\r\n        setInputValue(\"\")\r\n        adjustHeight(true)\r\n    }\r\n    return (\r\n\r\n        <div className=\"w-full py-4\">\r\n            <div className=\"relative max-w-xl w-full mx-auto \">\r\n                <Textarea\r\n                    id=\"ai-input-01\"\r\n                    placeholder=\"Type your message here...\"\r\n                    className={\r\n                        cn(\"max-w-xl bg-black/5 dark:bg-white/5 rounded-3xl pl-6 pr-16\",\r\n                            \"placholder:text-black/50 dark:placeholder:text-white/50\",\r\n                            \"border-none ring-black/20 dark:ring-white/20\",\r\n                            \"text-black dark:text-white text-wrap\",\r\n                            \"overflow-y-auto resize-none\",\r\n                            \"focus-visible:ring-0 focus-visible:ring-offset-0\",\r\n                            \"transition-[height] duration-100 ease-out\",\r\n                            \"leading-[1.2] py-[16px]\",\r\n                            \"min-h-[50px]\",\r\n                            \"max-h-[200px]\",\r\n                        )}\r\n                    ref={textareaRef}\r\n                    value={inputValue}\r\n                    onChange={(e) => {\r\n                        setInputValue(e.target.value)\r\n                        adjustHeight()\r\n                    }}\r\n                    onKeyDown={(e) => {\r\n                        if (e.key === \"Enter\" && !e.shiftKey) {\r\n                            e.preventDefault()\r\n                            handleReset()\r\n                        }\r\n                    }}\r\n                />\r\n                <div className={cn(\r\n                    \"absolute top-1/2 translation-y-1/2 rounded-xl bg-black/5 dark:bg-white/5 px-1 py-1 transition-all duration-200\",\r\n                    inputValue ? \"right-10\" : \"right-3\",\r\n                )}>\r\n                    <Mic className=\"w-4 h-4 text-black/70 dark:text-white/70\" />\r\n                </div>\r\n\r\n                <button\r\n                    className={cn(\r\n                        \"absolute top-1/2 translation-y-1/2 rounded-xl bg-black/5 dark:bg-white/5 px-2 py-1 transition-all duration-700\",\r\n                        inputValue ? \"block right-3 animate-slide-in cursor-pointer\" : \"hidden\"\r\n                    )}\r\n                >\r\n                    <CornerRightUp className=\"w-4 h-4 text-black/70 dark:text-white/70\" />\r\n                </button>\r\n            </div>\r\n\r\n        </div >\r\n    )\r\n\r\n}",
      "path": "/src/components/ghostui/ai-input/ai-input-01.tsx",
      "target": "/components/ghostui/ai-input-01.tsx"
    },
    {
      "type": "registry:hook",
      "content": "import { useCallback, useEffect, useRef, useState } from \"react\"\r\n\r\n\r\ninterface useAutoResizeTextareaProps {\r\n    minHeight: number;\r\n    maxHeight?: number;\r\n}\r\n\r\nexport function useAutoResizeTextarea({ minHeight, maxHeight }: useAutoResizeTextareaProps) {\r\n    const textareaRef = useRef<HTMLTextAreaElement>(null)\r\n    const adjustHeight = useCallback(\r\n        (reset?: boolean) => {\r\n            const textarea = textareaRef.current;\r\n            if (!textarea) return;\r\n            if (reset) {\r\n                textarea.style.height = `${minHeight}px`\r\n                return;\r\n            }\r\n\r\n            textarea.style.height = `${minHeight}px`;\r\n\r\n            const newHeight = Math.max(\r\n                minHeight,\r\n                Math.min(\r\n                    textarea.scrollHeight,\r\n                    maxHeight ?? Number.POSITIVE_INFINITY\r\n                )\r\n            );\r\n\r\n            textarea.style.height = `${newHeight}px`;\r\n\r\n        }, [maxHeight, minHeight]\r\n\r\n\r\n    );\r\n\r\n    useEffect(() => {\r\n        // set initial height\r\n        const textarea = textareaRef.current;\r\n        if (textarea) {\r\n            textarea.style.height = `${minHeight}px`;\r\n        }\r\n    }, [minHeight])\r\n    return {textareaRef, adjustHeight};\r\n\r\n}\r\n",
      "path": "/src/hooks/use-auto-resize-textarea.ts",
      "target": "/hooks/use-auto-resize-textarea.ts"
    }
  ]
}